topsis/__init__.py
topsis/__main__.py
topsis_agrim_102003549-1.0.2.dist-info/LICENSE
topsis_agrim_102003549-1.0.2.dist-info/METADATA
topsis_agrim_102003549-1.0.2.dist-info/WHEEL
topsis_agrim_102003549-1.0.2.dist-info/entry_points.txt
topsis_agrim_102003549-1.0.2.dist-info/top_level.txt
topsis_agrim_102003549-1.0.2.dist-info/RECORD
