Metadata-Version: 2.1
Name: topsis-agrim-102003549
Version: 1.0.2
Summary: It takes input file and gives ranking based on topsis score
Author: Agrim Sood
Author-email: agrimsood0635@gmail.com
License: MIT
Platform: UNKNOWN
Classifier: License :: OSI Approved :: MIT License
Classifier: Programming Language :: Python :: 3.6
Classifier: Programming Language :: Python :: 3.7
Classifier: Programming Language :: Python :: 3.8
License-File: LICENSE
